logger_decorator.py
logger_decorator-3.2.1.dist-info/METADATA
logger_decorator-3.2.1.dist-info/WHEEL
logger_decorator-3.2.1.dist-info/top_level.txt
logger_decorator-3.2.1.dist-info/RECORD
