Metadata-Version: 2.1
Name: logger-decorator
Version: 3.2.1
Author: Dmitriy Ignatiev
Author-email: dmitrignatyev@gmail.com
Requires-Python: >=3.6
Requires-Dist: loguru
